LICENSE.md
MANIFEST.in
README.md
setup.py
bin/ccbrowse
bin/cchtree-clean
bin/ccimport
bin/ccserver
ccbrowse/__init__.py
ccbrowse/algorithms.pyx
ccbrowse/autostr.py
ccbrowse/config.py
ccbrowse/exceptions.py
ccbrowse/hdf.pyx
ccbrowse/hdfeos.pyx
ccbrowse/profile.py
ccbrowse/rangelist.py
ccbrowse/server.py
ccbrowse/utils.py
ccbrowse.egg-info/PKG-INFO
ccbrowse.egg-info/SOURCES.txt
ccbrowse.egg-info/dependency_links.txt
ccbrowse.egg-info/not-zip-safe
ccbrowse.egg-info/requires.txt
ccbrowse.egg-info/top_level.txt
ccbrowse/colormaps/calipso-backscatter.json
ccbrowse/colormaps/cloudsat-reflectivity.json
ccbrowse/init-scripts/init
ccbrowse/init-scripts/systemd
ccbrowse/products/__init__.py
ccbrowse/products/calipso.py
ccbrowse/products/calipso_constants.py
ccbrowse/products/cloudsat.py
ccbrowse/products/naturalearth.py
ccbrowse/products/product.py
ccbrowse/storage/__init__.py
ccbrowse/storage/driver.py
ccbrowse/storage/fileref.py
ccbrowse/storage/filesystem.py
ccbrowse/storage/htree.py
ccbrowse/storage/memcache.py
ccbrowse/storage/null.py
ccbrowse/storage/router.py
ccbrowse/storage/sqlite.py
ccbrowse/template/README
ccbrowse/template/config.json
ccbrowse/template/profile.json
ccbrowse/template/wsgi.py
ccbrowse/template/layers/geography.json
ccbrowse/www/about.html
ccbrowse/www/index.html
ccbrowse/www/css/ccbrowse.css
ccbrowse/www/css/ccbrowse.css.map
ccbrowse/www/css/ccbrowse.scss
ccbrowse/www/css/colormap.scss
ccbrowse/www/css/config.rb
ccbrowse/www/css/globe.scss
ccbrowse/www/css/header.scss
ccbrowse/www/css/location-bar.scss
ccbrowse/www/css/map.scss
ccbrowse/www/css/navigation.scss
ccbrowse/www/css/page.scss
ccbrowse/www/css/tooltip.scss
ccbrowse/www/css/yaxis.scss
ccbrowse/www/font/asap/LICENSE.txt
ccbrowse/www/font/asap/bold.woff
ccbrowse/www/font/asap/regular.woff
ccbrowse/www/font/open-sans/LICENSE.txt
ccbrowse/www/font/open-sans/bold.woff
ccbrowse/www/font/open-sans/regular.woff
ccbrowse/www/globe/world-50m.json
ccbrowse/www/img/about.png
ccbrowse/www/img/about.svg
ccbrowse/www/img/bg.png
ccbrowse/www/img/bulb-active.png
ccbrowse/www/img/bulb-active.svg
ccbrowse/www/img/bulb-disabled.png
ccbrowse/www/img/bulb-disabled.svg
