Metadata-Version: 2.1
Name: ccbrowse
Version: 1.1.2
Summary: Web application for browsing data from the CALIPSO and CloudSat satellites
Home-page: https://ccplot.org/ccbrowse/
Author: Peter Kuma
Author-email: peter@peterkuma.net
License: MIT
Classifier: Programming Language :: Python
Classifier: Programming Language :: Python :: 3 :: Only
Classifier: Programming Language :: Python :: 3
Classifier: Programming Language :: Cython
Classifier: License :: OSI Approved :: MIT License
Classifier: Operating System :: POSIX
Classifier: Development Status :: 5 - Production/Stable
Classifier: Environment :: Console
Classifier: Environment :: Web Environment
Classifier: Intended Audience :: Science/Research
Classifier: Topic :: Scientific/Engineering :: Atmospheric Science
Requires-Python: >=3.7.0
License-File: LICENSE.md
